fair/__init__.py
fair/_version.py
fair/constants.py
fair/earth_params.py
fair/energy_balance_model.py
fair/exceptions.py
fair/fair.py
fair/interface.py
fair/defaults/__init__.py
fair/defaults/data/__init__.py
fair/defaults/data/ar6/__init__.py
fair/defaults/data/ar6/species_configs_properties.csv
fair/forcing/__init__.py
fair/forcing/ghg.py
fair/forcing/minor.py
fair/forcing/ozone.py
fair/forcing/aerosol/__init__.py
fair/forcing/aerosol/erfaci.py
fair/forcing/aerosol/erfari.py
fair/gas_cycle/__init__.py
fair/gas_cycle/ch4_lifetime.py
fair/gas_cycle/eesc.py
fair/gas_cycle/forward.py
fair/gas_cycle/inverse.py
fair/io/__init__.py
fair/io/fill_from.py
fair/io/param_sets.py
fair/structure/__init__.py
fair/structure/species.py
fair/structure/species_configs.py
fair/structure/units.py
fair-2.2.3.dist-info/licenses/LICENSE
fair-2.2.3.dist-info/METADATA
fair-2.2.3.dist-info/WHEEL
fair-2.2.3.dist-info/top_level.txt
fair-2.2.3.dist-info/RECORD
