Metadata-Version: 2.4
Name: fair
Version: 2.2.3
Summary: Finite-amplitude Impulse Response (FaIR) simple climate model
Home-page: https://github.com/OMS-NetZero/FAIR
Author: Chris Smith, Nicholas Leach, Stuart Jenkins, Richard Millar, Zeb Nicholls, Myles Allen
Author-email: c.j.smith1@leeds.ac.uk, nicholas.leach@stx.ox.ac.uk, stuart.jenkins@wadham.ox.ac.uk, richard.millar@ouce.ox.ac.uk, zebedee.nicholls@climate-energy-college.org, myles.allen@ouce.ox.ac.uk
License: Apache 2.0
Keywords: simple,climate,model,temperature,forcing,emissions,emulator
Classifier: Development Status :: 5 - Production/Stable
Classifier: Intended Audience :: Science/Research
Classifier: License :: OSI Approved :: Apache Software License
Classifier: Programming Language :: Python :: 3
Classifier: Programming Language :: Python :: 3.8
Classifier: Programming Language :: Python :: 3.9
Classifier: Programming Language :: Python :: 3.10
Classifier: Programming Language :: Python :: 3.11
Classifier: Programming Language :: Python :: 3.12
Classifier: Programming Language :: Python :: 3.13
Requires-Python: >=3.8, <4
License-File: LICENSE
Requires-Dist: matplotlib
Requires-Dist: numpy
Requires-Dist: pandas
Requires-Dist: pooch
Requires-Dist: scipy
Requires-Dist: tqdm
Requires-Dist: xarray
Provides-Extra: docs
Requires-Dist: ipython; extra == "docs"
Requires-Dist: pandoc; extra == "docs"
Requires-Dist: sphinx==6.2.1; extra == "docs"
Requires-Dist: sphinx_rtd_theme==1.2.0; extra == "docs"
Provides-Extra: tests
Requires-Dist: codecov; extra == "tests"
Requires-Dist: nbmake; extra == "tests"
Requires-Dist: netCDF4; extra == "tests"
Requires-Dist: pytest-cov; extra == "tests"
Requires-Dist: pytest-console-scripts; extra == "tests"
Requires-Dist: pytest; extra == "tests"
Provides-Extra: deploy
Requires-Dist: build; extra == "deploy"
Requires-Dist: twine; extra == "deploy"
Requires-Dist: setuptools; extra == "deploy"
Requires-Dist: wheel; extra == "deploy"
Provides-Extra: dev
Requires-Dist: ipython; extra == "dev"
Requires-Dist: pandoc; extra == "dev"
Requires-Dist: sphinx==6.2.1; extra == "dev"
Requires-Dist: sphinx_rtd_theme==1.2.0; extra == "dev"
Requires-Dist: nbstripout; extra == "dev"
Requires-Dist: jupyter; extra == "dev"
Requires-Dist: ipywidgets; extra == "dev"
Requires-Dist: ipython; extra == "dev"
Requires-Dist: codecov; extra == "dev"
Requires-Dist: nbmake; extra == "dev"
Requires-Dist: netCDF4; extra == "dev"
Requires-Dist: pytest-cov; extra == "dev"
Requires-Dist: pytest-console-scripts; extra == "dev"
Requires-Dist: pytest; extra == "dev"
Requires-Dist: build; extra == "dev"
Requires-Dist: twine; extra == "dev"
Requires-Dist: setuptools; extra == "dev"
Requires-Dist: wheel; extra == "dev"
Requires-Dist: bandit; extra == "dev"
Requires-Dist: black; extra == "dev"
Requires-Dist: flake8; extra == "dev"
Requires-Dist: isort; extra == "dev"
Requires-Dist: pydocstyle; extra == "dev"
Provides-Extra: dev-nodocs
Requires-Dist: nbstripout; extra == "dev-nodocs"
Requires-Dist: jupyter; extra == "dev-nodocs"
Requires-Dist: ipywidgets; extra == "dev-nodocs"
Requires-Dist: ipython; extra == "dev-nodocs"
Requires-Dist: codecov; extra == "dev-nodocs"
Requires-Dist: nbmake; extra == "dev-nodocs"
Requires-Dist: netCDF4; extra == "dev-nodocs"
Requires-Dist: pytest-cov; extra == "dev-nodocs"
Requires-Dist: pytest-console-scripts; extra == "dev-nodocs"
Requires-Dist: pytest; extra == "dev-nodocs"
Requires-Dist: build; extra == "dev-nodocs"
Requires-Dist: twine; extra == "dev-nodocs"
Requires-Dist: setuptools; extra == "dev-nodocs"
Requires-Dist: wheel; extra == "dev-nodocs"
Requires-Dist: bandit; extra == "dev-nodocs"
Requires-Dist: black; extra == "dev-nodocs"
Requires-Dist: flake8; extra == "dev-nodocs"
Requires-Dist: isort; extra == "dev-nodocs"
Requires-Dist: pydocstyle; extra == "dev-nodocs"
Dynamic: author
Dynamic: author-email
Dynamic: classifier
Dynamic: description
Dynamic: description-content-type
Dynamic: home-page
Dynamic: keywords
Dynamic: license
Dynamic: license-file
Dynamic: provides-extra
Dynamic: requires-dist
Dynamic: requires-python
Dynamic: summary
